{
  "productLists": [
    {
      "name": "Product List 1",
      "products": [
        {
          "name": "Sport Exhaust Pipe",
          "price": 1000,
          "image": "img/sport.webp",
          "brand": "sport"
        },
        {
          "name": "Cruise Exhaust Pipe",
          "price": 500,
          "image": "img/exhaust3.webp",
          "brand": "cruise"
        },
        {
          "name": "Turbo Exhaust Pipe",
          "price": 650,
          "image": "img/exhaust2.webp",
          "brand": "turbo"
        },
        {
          "name": "Blaze Exhaust Pipe",
          "price": 850,
          "image": "img/exhaust1.webp",
          "brand": "blaze"
        },
        {
          "name": "Sport Exhaust Pipe",
          "price": 1000,
          "image": "img/sport.webp",
          "brand": "sport"
        },
        {
          "name": "Cruise Exhaust Pipe",
          "price": 500,
          "image": "img/exhaust3.webp",
          "brand": "cruise"
        },
        {
          "name": "Turbo Exhaust Pipe",
          "price": 650,
          "image": "img/exhaust2.webp",
          "brand": "turbo"
        },
        {
          "name": "Blaze Exhaust Pipe",
          "price": 850,
          "image": "img/exhaust1.webp",
          "brand": "blaze"
        },
        {
          "name": "Sport Exhaust Pipe",
          "price": 1000,
          "image": "img/sport.webp",
          "brand": "sport"
        },
        {
          "name": "Cruise Exhaust Pipe",
          "price": 500,
          "image": "img/exhaust3.webp",
          "brand": "cruise"
        },
        {
          "name": "Turbo Exhaust Pipe",
          "price": 650,
          "image": "img/exhaust2.webp",
          "brand": "turbo"
        },
        {
          "name": "Blaze Exhaust Pipe",
          "price": 850,
          "image": "img/exhaust1.webp",
          "brand": "blaze"
        }
      ]
    },
    {
      "name": "Product List 2",
      "products": [
        {
          "name": "Product 1",
          "price": 39.99,
          "image": "https://example.com/product3.jpg",
          "brand": "Brand 3"
        },
        {
          "name": "Product 2",
          "price": 49.99,
          "image": "https://example.com/product4.jpg",
          "brand": "Brand 4"
        }
      ]
    },
    {
      "name": "Product List 3",
      "products": [
        {
          "name": "M 1000 RR",
          "price": 39800,
          "image": "img/schema/blob_https___www.bmw-motorrad.nl_9b51a408-731b-4f1d-a1c8-681f1d1b4e19",
          "brand": "bmw"
        },
        {
          "name": "M 1000 R",
          "price": 25500,
          "image": "img/schema/blob_https___www.bmw-motorrad.nl_9e06d2cb-7d27-415e-a968-cf2619762ced",
          "brand": "bmw"
        },
        {
          "name": "S 1000 RR",
          "price": 24200,
          "image": "img/schema/blob_https___www.bmw-motorrad.nl_1de80f39-1420-47dc-8cc0-95807b335155",
          "brand": "bmw"
        }
      ]
    }
  ]
}
